{"cameraMode":{"drawMode":0,"name":"Shaded","section":"Shading Mode"},"sceneLighting":false,"audioPlay":false,"sceneViewState":{"showFog":true,"showMaterialUpdate":false,"showSkybox":false,"showFlares":true,"showImageEffects":true,"showParticleSystems":true},"in2DMode":false,"pivot":{"x":-1.9885170459747315,"y":0.9752024412155151,"z":-0.9952235221862793},"rotation":{"x":-0.0679648220539093,"y":-0.1912459284067154,"z":0.01330988947302103,"w":-0.9791295528411865},"size":3.6000170707702638,"orthographic":false}